mycalc/calculator.py
pottery12315-0.0.1.dist-info/METADATA
pottery12315-0.0.1.dist-info/WHEEL
pottery12315-0.0.1.dist-info/top_level.txt
pottery12315-0.0.1.dist-info/RECORD
