Metadata-Version: 2.1
Name: pottery12315
Version: 0.0.1
Summary: oss-dev my calculator 0001
Home-page: https://github.com/sejin-chun/calc0001
Download-URL: https://github.com/sejin-chun/calc0001/archive/refs/tags/v0.0.1.zip
Author: sejinchun
Author-email: sjchun@dau.ac.kr
License: UNKNOWN
Platform: UNKNOWN
Classifier: Programming Language :: Python :: 3
Classifier: Operating System :: OS Independent
Requires-Dist: pytest
